qlab/__init__.py
qlab/backend.py
qlab/bloch.py
qlab/demos.py
qlab/experiment.py
qlab/py.typed
qlab/runner.py
qlab/store.py
qex-0.1.1.dist-info/METADATA
qex-0.1.1.dist-info/WHEEL
qex-0.1.1.dist-info/top_level.txt
qex-0.1.1.dist-info/RECORD
