Metadata-Version: 2.4
Name: qex
Version: 0.1.1
Summary: A lightweight experiment-runner and lab notebook for quantum computing
Author: qlab contributors
License: Apache-2.0
Project-URL: Homepage, https://github.com/AndreaPallotta/qlab
Project-URL: Documentation, https://github.com/AndreaPallotta/qlab#readme
Project-URL: Repository, https://github.com/AndreaPallotta/qlab
Project-URL: Issues, https://github.com/AndreaPallotta/qlab/issues
Keywords: quantum,quantum-computing,cirq,experiments,quantum-simulation,bloch-sphere
Classifier: Development Status :: 3 - Alpha
Classifier: Intended Audience :: Science/Research
Classifier: Intended Audience :: Developers
Classifier: License :: OSI Approved :: Apache Software License
Classifier: Operating System :: OS Independent
Classifier: Programming Language :: Python :: 3
Classifier: Programming Language :: Python :: 3.12
Classifier: Programming Language :: Python :: 3.13
Classifier: Topic :: Scientific/Engineering :: Physics
Classifier: Topic :: Software Development :: Libraries :: Python Modules
Requires-Python: >=3.12
Requires-Dist: cirq>=1.6.1
Requires-Dist: numpy>=1.24.0
Provides-Extra: dev
Requires-Dist: pytest>=7.0.0; extra == "dev"
Requires-Dist: pytest-cov>=4.0.0; extra == "dev"
Requires-Dist: black>=23.0.0; extra == "dev"
Requires-Dist: ruff>=0.1.0; extra == "dev"
Requires-Dist: mypy>=1.0.0; extra == "dev"
